<?xml version="1.0" encoding="utf-8"?>
<Content ID="x41940" Name="FDSCI 208" Layout="byuidefault.xsl"><Title type="string" label="Title" readonly="false" hidden="false" required="true">FDSCI 208</Title><Abstract type="string" label="Abstract" readonly="false" hidden="false" required="true">FDSCI 208</Abstract><xPower Type="GroupStart" Name="SEOGroup" label="SEO Group" readonly="false" hidden="false" required="false" Expanded="false" GroupStart=""><BrowserBarTitle type="string" label="Browser Bar Title" readonly="false" hidden="false" required="false"/><MetaDescription type="string" label="Meta Description" readonly="false" hidden="false" required="false"/><NoFollow type="boolean" label="No Follow" readonly="false" hidden="true" required="false">false</NoFollow><NoIndex type="boolean" label="No Index" readonly="false" hidden="true" required="false">false</NoIndex><NoODP type="boolean" label="No ODP" readonly="false" hidden="true" required="false">false</NoODP><Priority type="enumeration" label="Priority" readonly="false" hidden="true" required="false" values="0.0 0.1 0.2 0.3 0.4 0.5 0.6 0.7 0.8 0.9 1.0">0.5</Priority></xPower><xPower Type="GroupStart" Name="PageOptions" label="Page Options" readonly="false" hidden="false" required="false" Expanded="false" GroupStart=""><HideTitle type="boolean" label="Hide Title" readonly="false" hidden="false" required="false">false</HideTitle><Hideleftnavigation type="boolean" label="Hide left navigation" readonly="false" hidden="false" required="false">false</Hideleftnavigation></xPower><BodyCopy type="dhtml" label="Body Copy" readonly="false" hidden="false" required="false" Height=""><![CDATA[<h3><strong>Introduction to Robotics</strong></h3>
<hr />
<p></p>
<h6>Course Description</h6>
<p style="padding-left: 30px;">This course provides a hands-on approach to the fundamentals of robotics, including how robots sense, move, and make decisions.&nbsp; Students will build and configure robots to solve basic real-world problems and analyze their performance.&nbsp; The class will also explore ethical and environmental issues related to robotics. &nbsp;</p>
<h6>Contents &amp; Topics<strong>&nbsp;&nbsp;</strong></h6>
<ul>
<li>Introduction to Robotics</li>
<li>Simple Machines</li>
<li>Actuators</li>
<li>Sensors</li>
<li>Controllers</li>
<li>Engineering Design &nbsp;</li>
</ul>
<h6>Goals and Objectives</h6>
<ol>
<li>Understand and apply fundamentals of problem solving, design, and analysis as used in STEM (Science, Technology, Engineering, and Math) disciplines.</li>
<li>Demonstrate an understanding of basic principles in designing and building robots including the use of sensors, actuators, controllers, and mechanical structures.</li>
<li>Demonstrate an understanding of simple machines and mechanisms used in robotics, such as gears, pulleys, levers, belts, and wheels.</li>
<li>Demonstrate an understanding of the basic characteristic response of sensors and how to interface them.</li>
<li>Demonstrate an understanding of actuator usage to convert energy to simple linear or rotary motion.</li>
<li>Demonstrate the ability to program a basic robot controller (e.g., the Lego NXT controller).</li>
<li>Understand moral and ethical issues relating to robotics and automation.</li>
<li>Develop and demonstrate effective teamwork skills. <strong style="font-family: inherit; font-size: inherit; font-style: inherit; font-variant: inherit; line-height: inherit;">&nbsp;&nbsp;</strong></li>
</ol>
<h6>Course Requirements &nbsp;</h6>
<ul>
<li>Labs</li>
<li>Projects</li>
<li>Exams</li>
<li>Final Projects</li>
<li>Quizzes Assignments-Study Guides</li>
<li>Post-lab Analysis &nbsp;</li>
</ul>
<h6>Course Prerequisites</h6>
<ul>
<li>Completion of FDSCI101 with a D- or higher</li>
<li>Completion of FDENG101 with a D- or higher</li>
<li>Completion of FDMAT108 with a D- or higher</li>
</ul>
<h6>Semesters Taught</h6>
<p style="padding-left: 30px;">Winter, Spring, Fall</p>
<h6>Course Lead</h6>
<h2><img alt="Garth Miller" src="https://web.byui.edu/Directory/Employee/millerg.jpg" /><br />Garth Miller</h2>
<p>E-MAIL <br /><a href="mailto:millerg@byui.edu">millerg@byui.edu</a></p>]]></BodyCopy><xPower Type="GroupStart" Name="PageComponents" label="Page Components" readonly="false" hidden="false" required="false" Expanded="" GroupStart=""><xPower Type="List" Name="OptionalColumnComponent" label="Optional Column Components" readonly="false" hidden="false" required="false" Expanded="" List=""><xpowercomponent_Optional Type="Component" Component="" Name="Optional" readonly="false" hidden="false" required="false" CompTypes="FacebookComponent;Image;ColumnTextComponent;Media;Quote" Expanded="false"/></xPower><xPower Type="Component" Name="QuickLinksColumn1" label="QuickLinks Column 1" readonly="false" hidden="false" required="false" Component="" CompTypes="QuickLinksComponent"/><xPower Type="Component" Name="QuickLinksColumn2" label="QuickLinks Column 2" readonly="false" hidden="false" required="false" Component="" CompTypes="QuickLinksComponent"/><xPower Type="Component" Name="QuickLinksColumn3" label="QuickLinks Column 3" readonly="false" hidden="false" required="false" Component="" CompTypes="QuickLinksComponent"/></xPower><xPower Type="Component" Name="HighlightedLinks" label="Highlighted Links" readonly="false" hidden="false" required="false" Component="" CompTypes="HighlightedLinksComponent" Expanded="false"/><xPower Type="List" Name="ContentSnippet" label="Content Snippet" readonly="false" hidden="false" required="false" Expanded="false"><xPower Type="Component" Name="ContentSnippet" readonly="false" hidden="false" required="false" Component="" CompTypes="ContentSnippet"/></xPower><xPower Type="Navigation" Name="AncestorNavigation" label="Ancestor Navigation" readonly="true" hidden="true" required="false" Expanded="false" Navigation="Ancestors" GenerationOrder="down" StartPage="x5" MaxNodes="" MaxDepth="" Query=""/><xPower Type="Component" Name="SiteControl" label="Site Control" readonly="true" hidden="false" required="false" Component="x17649" CompTypes="SiteControl" Expanded="false"/></Content>
