<?xml version="1.0"?>
<!--*** Ingeniux CMS 7.5.118 - http://www.ingeniux.com ***-->
<EventsDetail ID="x48271" Name="Last Voice Standing" Layout="byuidefault.xsl"><Title type="string" label="Event Title" readonly="false" hidden="false" required="true">Last Voice Standing</Title><Abstract type="string" label="Abstract" readonly="false" hidden="false" required="true">Last Voice Standing</Abstract><xPower Type="GroupStart" GroupStart="" Name="SEOGroup" label="SEO Group" readonly="false" hidden="false" required="false" Expanded="true"><BrowserBarTitle type="string" label="Browser Bar Title" readonly="false" hidden="false" required="false">Last Voice Standing - BYU-Idaho Talent Activities</BrowserBarTitle><MetaDescription type="string" label="Meta Description" readonly="false" hidden="false" required="false">It's not American Idol, it's not the Voice...it's the Last Voice Standing!

There is no reason for you to be bored here in Rexburg. Every week there BYU-Idaho Talent Activities has free workshops in a variety of hobbies and interests. (BYUI, Rexburg, what to do in Rexburg, Fun things in Rexburg)</MetaDescription><NoFollow type="boolean" label="No Follow" readonly="false" hidden="true" required="false">false</NoFollow><NoIndex type="boolean" label="No Index" readonly="false" hidden="true" required="false">false</NoIndex><NoODP type="boolean" label="No ODP" readonly="false" hidden="true" required="false">false</NoODP><Priority type="enumeration" values="0.0 0.1 0.2 0.3 0.4 0.5 0.6 0.7 0.8 0.9 1.0" label="Priority" readonly="false" hidden="true" required="false">0.5</Priority></xPower><BodyCopy type="dhtml" label="Event Details" readonly="false" hidden="false" required="false"><![CDATA[<p>Like American Idol? Like the Voice? The Last Voice Standing is our version. Auditions will be held at the beginning of the semester. Singers will be eliminated throughout the semester every Wed. in the Crossroads at 7 p.m. with the final show in the Kirkham on July 2 at 8 p.m.&nbsp;</p>
<p>Auditions are May 14.</p>
<p>To sign up to audition click on the link below:</p>
<p>https://docs.google.com/document/d/1GuHCHVn3lYpiEEUdy_yxiTuGcdmLB_GROs-zFzoHOKw/edit</p>
<p><br /><br /><br /><em> </em></p>
<hr />
<p><iframe frameborder="0" height="240" scrolling="no" src="http://www.facebook.com/plugins/like.php?href=http%3A%2F%2Fwww.facebook.com%2Fbyuitalent&amp;send=false&amp;layout=standard&amp;width=150&amp;show_faces=true&amp;action=like&amp;colorscheme=light&amp;font&amp;height=80&amp;appId=124396454327538" style="border: none; overflow: hidden; width: 230px; height: 55px;" width="320"></iframe> &nbsp;<a class="extLink" href="http://www.byui.edu/activities/get-involved/talent-student-leader-information" title="Volunteer Application" target="_blank"> <img alt="Audition Sign-Up" height="21" onmouseout="this.src='Images/activities/talent/buttons/Auditions-Button-up(1).gif';" onmouseover="this.src='Images/activities/talent/buttons/Auditions-Button-down(0).gif';" src="Images/activities/talent/buttons/Auditions-Button-up(1).gif" style="width: 80px; height: 21px; padding: 0px; margin: 0px;" title="Audition Sign-Up" width="70" />&nbsp;(https://docs.google.com/document/d/1GuHCHVn3lYpiEEUdy_yxiTuGcdmLB_GROs-zFzoHOKw/edit)&nbsp;<img alt="Volunteer Application" height="21" onmouseout="this.src='Images/activities/talent/buttons/volunteer-Button-up(1).gif';" onmouseover="this.src='Images/activities/talent/buttons/volunteer-Button-down(1).gif';" src="Images/activities/talent/buttons/volunteer-Button-up(1).gif" style="width: 80px; height: 21px; padding: 0px; margin: 0px;" title="Volunteer" width="70" /></a> &nbsp;<a href="mailto:talentactiv@gmail.com" title="Email Link"><img alt="Email Us" height="21" onmouseout="this.src='Images/activities/talent/buttons/Email-Button-up(0).gif';" onmouseover="this.src='Images/activities/talent/buttons/Email-Button-down(0).gif';" src="Images/activities/talent/buttons/Email-Button-up(0).gif" style="width: 80px; height: 21px; padding: 0px; margin: 0px;" title="Email" width="70" /></a>&nbsp;&nbsp;<a class="extLink" href="http://byui.universitytickets.com/user_pages/event_listings.aspx?id=110" title="Ticket Office link" target="_blank"> </a><br /><em> </em></p>
<hr />
<p></p>]]></BodyCopy><xPower Type="GroupStart" GroupStart="" Name="Semesters" label="Available Semesters" readonly="false" hidden="false" required="false" Expanded="false"><AvailableFall type="boolean" label="Available Fall" readonly="false" hidden="false" required="false">true</AvailableFall><AvailableWinter type="boolean" label="Available Winter" readonly="false" hidden="false" required="false">true</AvailableWinter><AvailableSpring type="boolean" label="Available Spring" readonly="false" hidden="false" required="false">true</AvailableSpring><AvailableSummer type="boolean" label="Available Summer" readonly="false" hidden="false" required="false">true</AvailableSummer><xPower Type="List" List="Date" Name="DateElements" label="Dates" readonly="false" hidden="false" required="false" display="localdateshort" Expanded="false"><Date type="date" readonly="false" hidden="false" required="false" display="localdateshort" Expanded="false"></Date></xPower><AdditionalInformation type="dhtml" label="Additional Information" readonly="false" hidden="false" required="false"><![CDATA[]]></AdditionalInformation></xPower><EventImage type="imagefile" label="Event Image" readonly="false" hidden="false" required="true" Width="360" Height="240" Alignment="" Border="" Expanded="true" AlternateText="" HSpace="" VSpace="">activities/talent/Guitars Unplugged - Fall 2012/DSC_0199cr.jpg</EventImage><xPower Type="List" List="Images" Name="Images" label="Gallery Images" readonly="false" hidden="false" required="false" Width="" Border="" Alignment="" Expanded="false" Height=""><Images type="imagefile" readonly="false" hidden="false" required="false" Width="" Border="" Alignment="" Expanded="true" Height="" AlternateText="" HSpace="" VSpace=""></Images></xPower><xPower Type="Component" Component="x6793" Name="HighlightedLinks" label="Highlighted Links" readonly="false" hidden="false" required="false" CompTypes="HighlightedLinksComponent" Expanded="false"/><xPower Type="Navigation" StartPage="x5" MaxDepth="" MaxNodes="" GenerationOrder="down" Navigation="Ancestors" Query="" Name="AncestorNavigation" label="Ancestor Navigation" readonly="true" hidden="true" required="false" Expanded="false"/><xPower Type="Component" Component="x6784" Name="SiteControl" label="Site Control" readonly="true" hidden="false" required="false" CompTypes="SiteControl" Expanded="false"/></EventsDetail>
