<?xml version="1.0"?>
<!--*** Ingeniux CMS 8.0.101 - http://www.ingeniux.com ***-->
<QuickLinksComponent ID="x66315" Name="Collecting Areas" IsComponent="true"><Title type="string" label="Title" readonly="false" hidden="false" required="true">Collecting Areas</Title><xPower Type="List" List="xpowerlink_Link" Name="Links" label="Links" readonly="false" hidden="false" required="false" LinkText="" Target="" Link="" Expanded="true"><xPower Type="Link" Link="x50870" Name="Link" readonly="false" hidden="false" required="false" LinkText="Campus History" Target="" Expanded="false" URL=""><Exports></Exports></xPower><xPower Type="Link" Link="x50829" Name="Link" readonly="false" hidden="false" required="false" LinkText="Local History" Target="" Expanded="false" URL=""><Exports></Exports></xPower></xPower></QuickLinksComponent>
